setup.py
manish_package/Binomialdistribution.py
manish_package/Gaussiandistribution.py
manish_package/Generaldistribution.py
manish_package/__init__.py
manish_package.egg-info/PKG-INFO
manish_package.egg-info/SOURCES.txt
manish_package.egg-info/dependency_links.txt
manish_package.egg-info/not-zip-safe
manish_package.egg-info/top_level.txt