Metadata-Version: 1.0
Name: manish-package
Version: 0.4
Summary: Gaussian distributions
Home-page: UNKNOWN
Author: Manish Bhurtel
Author-email: data_scientist@gmail.com
License: UNKNOWN
Platform: UNKNOWN
